setup.py
Circles/__init__.py
Circles/circles.py
Circles.egg-info/PKG-INFO
Circles.egg-info/SOURCES.txt
Circles.egg-info/dependency_links.txt
Circles.egg-info/requires.txt
Circles.egg-info/top_level.txt